poetbricks/__init__.py
poetbricks/main.py
poetbricks-0.1.2.dist-info/LICENSE
poetbricks-0.1.2.dist-info/METADATA
poetbricks-0.1.2.dist-info/WHEEL
poetbricks-0.1.2.dist-info/entry_points.txt
poetbricks-0.1.2.dist-info/RECORD
