Metadata-Version: 2.1
Name: poetbricks
Version: 0.1.2
Summary: A little CLI tool to create requirements.txt file that are compatible with databricks. The produced requirement file can be uploaded to databricks to set up any custom compute.
License: GPL-3.0-or-later
Keywords: poetry,databricks,requirement,pip
Author: Lars Vögtlin
Requires-Python: >=3.11
Classifier: Development Status :: 4 - Beta
Classifier: License :: OSI Approved :: GNU General Public License v3 or later (GPLv3+)
Classifier: Programming Language :: Python
Classifier: Programming Language :: Python :: 3
Classifier: Programming Language :: Python :: 3.11
Classifier: Programming Language :: Python :: 3.12
Classifier: Programming Language :: Python :: 3.13
Requires-Dist: requests (>=2.32.3,<3.0.0)
